teeplot/__init__.py
teeplot/teeplot.py
teeplot-1.4.2.dist-info/AUTHORS.rst
teeplot-1.4.2.dist-info/LICENSE
teeplot-1.4.2.dist-info/METADATA
teeplot-1.4.2.dist-info/WHEEL
teeplot-1.4.2.dist-info/top_level.txt
teeplot-1.4.2.dist-info/RECORD
