Metadata-Version: 2.1
Name: teeplot
Version: 1.4.2
Summary: teeplot automatically saves a copy of rendered Jupyter notebook plots
Home-page: https://github.com/mmore500/teeplot
Author: Matthew Andres Moreno
Author-email: m.more500@gmail.com
License: MIT license
Keywords: teeplot
Platform: UNKNOWN
Classifier: Development Status :: 2 - Pre-Alpha
Classifier: Intended Audience :: Developers
Classifier: License :: OSI Approved :: MIT License
Classifier: Natural Language :: English
Classifier: Programming Language :: Python :: 3
Classifier: Programming Language :: Python :: 3.8
Classifier: Programming Language :: Python :: 3.9
Classifier: Programming Language :: Python :: 3.10
Classifier: Programming Language :: Python :: 3.11
Requires-Python: >=3.8
Requires-Dist: keyname
Requires-Dist: matplotlib
Requires-Dist: python-slugify
Requires-Dist: distutils-strtobool
Requires-Dist: typing-extensions
